pynoon/__init__.py
pynoon/const.py
pynoon-0.0.16.dist-info/LICENSE
pynoon-0.0.16.dist-info/METADATA
pynoon-0.0.16.dist-info/WHEEL
pynoon-0.0.16.dist-info/top_level.txt
pynoon-0.0.16.dist-info/RECORD
