Metadata-Version: 2.1
Name: pynoon
Version: 0.0.16
Summary: Python library for Noon Home
Home-page: http://github.com/alistairg/pynoon
Author: Alistair Galbraith
Author-email: github@alistairs.net
License: MIT
Platform: UNKNOWN
Classifier: Development Status :: 3 - Alpha
Classifier: License :: OSI Approved :: MIT License
Classifier: Operating System :: OS Independent
Classifier: Programming Language :: Python
Classifier: Programming Language :: Python :: 3.4
Classifier: Topic :: Home Automation
Classifier: Topic :: Software Development :: Libraries :: Python Modules
Requires-Dist: requests
Requires-Dist: websocket-client
